moirai/__init__.py
moirai/version.py
moirai/checkpoint/__init__.py
moirai/checkpoint/checkpoint.py
moirai/config/__init__.py
moirai/config/config.py
moirai/config/utils.py
moirai/data/__init__.py
moirai/data/dataset.py
moirai/data/loader/__init__.py
moirai/data/loader/builder.py
moirai/data/loader/perfetcher.py
moirai/device/__init__.py
moirai/device/device.py
moirai/dist/__init__.py
moirai/dist/dist.py
moirai/entry_point/__init__.py
moirai/entry_point/easytrain.py
moirai/evaluator/__init__.py
moirai/evaluator/metric.py
moirai/launcher/__init__.py
moirai/launcher/launcher.py
moirai/logging/__init__.py
moirai/logging/logger.py
moirai/model/__init__.py
moirai/model/builder.py
moirai/model/module.py
moirai/optim/__init__.py
moirai/optim/builder.py
moirai/optim/custom/__init__.py
moirai/optim/custom/lr_scheduler/__init__.py
moirai/optim/custom/lr_scheduler/cosine_warmup_lr.py
moirai/optim/custom/optim/__init__.py
moirai/optim/custom/optim/lamb.py
moirai/runner/__init__.py
moirai/runner/runner.py
moirai/utils/__init__.py
moirai/utils/env.py
moirai/utils/misc.py
moirai/utils/timer.py
moirai_ts-0.0.1.dist-info/METADATA
moirai_ts-0.0.1.dist-info/WHEEL
moirai_ts-0.0.1.dist-info/entry_points.txt
moirai_ts-0.0.1.dist-info/licenses/LICENSE
moirai_ts-0.0.1.dist-info/RECORD
