Metadata-Version: 2.4
Name: moirai-ts
Version: 0.0.1
Summary: Simple and powerful deep learning pipeline framework under pytorch.
Project-URL: Tracker, https://github.com/dunzane/moirai/issues
Project-URL: Source, https://github.com/dunzane/moirai
Author-email: dunzane <dunzane@outlook.com>
License: Apache License 2.0
License-File: LICENSE
Keywords: deep learning,pytorch
Classifier: License :: OSI Approved :: Apache Software License
Classifier: Operating System :: OS Independent
Classifier: Programming Language :: Python :: 3
Classifier: Programming Language :: Python :: 3.7
Classifier: Programming Language :: Python :: 3.8
Classifier: Programming Language :: Python :: 3.9
Classifier: Topic :: Utilities
Requires-Python: >=3.7
Requires-Dist: tensorboard
Requires-Dist: torch>=1.4
Requires-Dist: tqdm
Requires-Dist: typer
